view/__init__.py
view/bomber.py
view/view.py
siamviews-1.1.1.dist-info/LICENSE
siamviews-1.1.1.dist-info/METADATA
siamviews-1.1.1.dist-info/WHEEL
siamviews-1.1.1.dist-info/top_level.txt
siamviews-1.1.1.dist-info/RECORD
